Metadata-Version: 1.0
Name: max-dist-98
Version: 0.1
Summary: Gaussian distributions
Home-page: UNKNOWN
Author: Max Rim
Author-email: UNKNOWN
License: UNKNOWN
Platform: UNKNOWN
